{"fetched_at": "2026-06-22T14:07:08.423241", "video_id": "0p64jgsrfqg", "info": {"id": "0p64jgsrfqg", "title": "Lê Lợi cố thủ ở Sách Khôi | Khởi nghĩa Lam Sơn #suluoc #tomtatlichsu #lichsuvietnam", "channel": "Sử Lược - Tóm Tắt Lịch Sử", "channel_id": "UCJDueHzfSEXmgMhmKIa9esQ", "description": "Trong lúc hiểm nguy nhất của khởi nghĩa Lam Sơn, Lê Lợi buộc phải cố thủ tại Sách Khôi, đối mặt với vòng vây khắc nghiệt của quân Minh. Chính tại đây, ý chí kiên cường và chiến lược linh hoạt đã giúp nghĩa quân giữ vững hy vọng sống còn.", "upload_date": "20260519", "duration": 45, "view_count": 7499, "like_count": 82, "comment_count": 1, "tags": ["tóm tắt lịch sử", "lịch sử việt nam", "sử lược", "đại việt", "tóm tắt", "tóm tắt nhanh", "nhà hậu lê", "lê sơ", "khởi nghĩa lam sơn", "lê lợi", "quân minh"], "categories": ["22"], "thumbnails": [{"url": "https://i.ytimg.com/vi/0p64jgsrfqg/hqdefault.jpg", "id": "high"}], "webpage_url": "https://www.youtube.com/watch?v=0p64jgsrfqg", "subtitles": {}, "automatic_captions": {}, "language": "vi", "audio_language": "vi", "height": 1080, "availability": "public", "playable_in_embed": true, "is_live": false, "live_status": "none", "was_live": false, "license": true, "topic_categories": []}}