{"fetched_at": "2026-06-22T14:07:08.423241", "video_id": "CvpKrqE5yoA", "info": {"id": "CvpKrqE5yoA", "title": "Tóm tắt: Lịch sử Timor Leste - Đông Timor | Tóm tắt lịch sử Thế Giới", "channel": "Sử Lược - Tóm Tắt Lịch Sử", "channel_id": "UCJDueHzfSEXmgMhmKIa9esQ", "description": "#suluoc #tomtatlichsu #lichsudongnama #timorleste \n\n► Theo dõi Sử Lược tại:\nFacebook: https://www.facebook.com/suluoctomtatlichsu\nCâu Chuyện Lịch Sử: https://www.youtube.com/@suluoc2\n► Liên hệ quảng cáo qua fanpage Facebook\n► Ủng hộ kênh (donate) bằng cách trở thành \"Hội viên\" hoặc sử dụng nút \"Cảm ơn\" các bạn nhé!\n► Like & Subcribe để theo dõi những video tiếp theo!\n\n------------------------------\n\nĐông Timor hay Timor-Leste, tên chính thức là Cộng hòa Dân chủ Timor-Leste, là một quốc gia ở khu vực Đông Nam Á, bao gồm nửa phía Đông của đảo Timor, những đảo lân cận gồm Atauro và Jaco và Oecussi-Ambeno, một phần nằm ở phía Tây Bắc của đảo, trong Tây Timor của Indonesia. Đông Timor là một đất nước nhỏ bé với 15.410 km² cách thành phố Darwin, Úc khoảng 640 km về phía tây bắc.\nBị thực dân Bồ Đào Nha đô hộ vào thế kỷ XVI, Đông Timor được biết đến với tên gọi Timor thuộc Bồ Đào Nha trong hàng thế kỷ. Nước này bị xâm lăng và chiếm đóng bởi Indonesia vào năm 1975 và trở thành tỉnh thứ 27 của Indonesia một năm sau đó. Sau cuộc bỏ phiếu để tự quyết định số phận đất nước do Liên Hợp Quốc tài trợ vào năm 1999, Indonesia rút khỏi lãnh thổ và Đông Timor trở thành quốc gia có chủ quyền được thành lập đầu tiên trong thế kỷ XXI và thiên niên kỷ thứ 3 vào ngày 20 tháng 5 năm 2002. Cùng với Philippines, Đông Timor là một trong hai nước ở châu Á có đa số người dân theo Công giáo.\nĐông Timor là một trong những nước có GDP trên đầu người thấp nhất thế giới. Tuy nhiên, chỉ số phát triển con người (HDI) lại tương ứng với mức trung bình của sự phát triển con người và đặt Đông Timor thứ 142 trong các quốc gia trên thế giới.\n\nNội dung:\n0:00 Mở đầu\n0:35 Buổi đầu lịch sử\n1:33 Thuộc địa của Bồ Đào Nha\n4:04 Indonesia chiếm đóng Timor Leste\n5:12 Timor Leste độc lập\n6:55 Timor Leste ngày nay", "upload_date": "20230428", "duration": 454, "view_count": 55868, "like_count": 404, "comment_count": 20, "tags": ["sử lược", "tóm tắt lịch sử", "lịch sử thế giới", "tóm tắt nhanh", "tóm tắt", "lịch sử đông nam á", "thực dân bồ đào nha", "timor thuộc bồ đào nha", "đông timor", "timor leste", "indonesia chiếm đóng timor leste"], "categories": ["22"], "thumbnails": [{"url": "https://i.ytimg.com/vi/CvpKrqE5yoA/hqdefault.jpg", "id": "high"}], "webpage_url": "https://www.youtube.com/watch?v=CvpKrqE5yoA", "subtitles": {}, "automatic_captions": {}, "language": "vi", "audio_language": "vi", "height": 1080, "availability": "public", "playable_in_embed": true, "is_live": false, "live_status": "none", "was_live": false, "license": true, "topic_categories": []}}